<?xml version="1.0" encoding="UTF-8" ?><tns:order xmlns:jca="http://xmlns.oracle.com/pcbpel/wsdl/jca/" xmlns:ns2="http://xmlns.oracle.com/pcbpel/adapter/file/POApplication/PoProcessing/WritePOFileService" xmlns:ns1="http://oracle.com/sca/soapservice/POApplication/PoProcessing/ReceivePO" xmlns:wsdl="http://schemas.xmlsoap.org/wsdl/" xmlns:plt="http://schemas.xmlsoap.org/ws/2003/05/partner-link/" xmlns:tns="http://www.example.org/ns/intorder"><tns:customerId>2</tns:customerId><tns:orderId>100</tns:orderId><tns:payMethod>credit</tns:payMethod><tns:shipMethod>two_day</tns:shipMethod><tns:status>initial</tns:status><tns:creditCard><tns:cardType>VISA</tns:cardType><tns:cardNumber>1234-1234-1234-1234</tns:cardNumber></tns:creditCard><tns:items><tns:item><tns:prodId>SKU301</tns:prodId><tns:prodName>iPod 1Gb Shuffle</tns:prodName><tns:price>45</tns:price><tns:qty>3</tns:qty></tns:item></tns:items></tns:order>